gpi/GLObjects.py
gpi/__init__.py
gpi/associate.py
gpi/canvasGraph.py
gpi/canvasScene.py
gpi/catalog.py
gpi/cmd.py
gpi/config.py
gpi/console.py
gpi/dataproxy.py
gpi/defaultTypes.py
gpi/defines.py
gpi/docs.py
gpi/ebe.py
gpi/edge.py
gpi/functor.py
gpi/gpi_pb2.py
gpi/gpi_pb2_grpc.py
gpi/launch.py
gpi/layoutWindow.py
gpi/library.py
gpi/loader.py
gpi/logger.py
gpi/macroNode.py
gpi/mainWindow.py
gpi/make.py
gpi/network.py
gpi/node.py
gpi/nodeAPI.py
gpi/nodeQueue.py
gpi/nodeTemplate.py
gpi/node_profiler.py
gpi/numba_stub.py
gpi/numpyqt.py
gpi/parallel.py
gpi/port.py
gpi/qtapi.py
gpi/remote.py
gpi/runnable.py
gpi/shortcuts.py
gpi/stateMachine.py
gpi/syntax.py
gpi/sysspecs.py
gpi/topsort.py
gpi/update.py
gpi/widgets.py
gpi/graphics/devlogo.png
gpi/graphics/docslogo.png
gpi/graphics/gpi.icns
gpi/graphics/iclogo.png
gpi/graphics/logo.png
gpi/graphics/networkicon.png
gpi/graphics/slogo.png
gpi/include/PyFI/PyFI.h
gpi/include/PyFI/PyFIArray.cpp
gpi/include/PyFI/PyFIArray_WrappedEigen.cpp
gpi/include/PyFI/PyFIArray_WrappedFFTW.cpp
gpi/include/PyFI/PyFIArray_WrappedNUMPY.cpp
gpi/include/PyFI/PyFIMacros.h
gpi/include/PyFI/PyFunctionIF.cpp
gpi/include/PyFI/backtrace.cpp
gpi/include/PyFI/basic.cpython-37m-darwin.so
gpi/include/PyFI/basic.cpython-39-darwin.so
gpi/include/PyFI/basic_PyMOD.cpp
gpi/include/PyFI/eigen.cpython-37m-darwin.so
gpi/include/PyFI/eigen.cpython-39-darwin.so
gpi/include/PyFI/eigen_PyMOD.cpp
gpi/include/PyFI/eigen_test.py
gpi/include/PyFI/embedded_script.py
gpi/include/PyFI/mymath.cpython-37m-darwin.so
gpi/include/PyFI/mymath.cpython-39-darwin.so
gpi/include/PyFI/mymath_PyMOD.cpp
gpi/include/PyFI/template_PyMOD.cpp
gpi/include/PyFI/template_test.py
gpi/include/PyFI/test.py
gpi/include/PyFI/test_basic.py
gpi/include/PyFI/__pycache__/eigen_test.cpython-37.pyc
gpi/include/PyFI/__pycache__/eigen_test.cpython-39.pyc
gpi/include/PyFI/__pycache__/embedded_script.cpython-37.pyc
gpi/include/PyFI/__pycache__/embedded_script.cpython-39.pyc
gpilab-1.4.8.dist-info/AUTHORS
gpilab-1.4.8.dist-info/COPYING
gpilab-1.4.8.dist-info/COPYING.LESSER
gpilab-1.4.8.dist-info/LICENSE
gpilab-1.4.8.dist-info/METADATA
gpilab-1.4.8.dist-info/WHEEL
gpilab-1.4.8.dist-info/top_level.txt
gpilab-1.4.8.dist-info/RECORD
