Metadata-Version: 2.1
Name: gpilab
Version: 1.4.8
Summary: Graphical Programming Interface
Home-page: https://github.com/gpilab/framework
Author: AbdulRahman Alfayad
Author-email: alfayad.abdulrahman@mayo.edu
License: GNU
Platform: UNKNOWN
Requires-Python: >=3.7
License-File: LICENSE
License-File: COPYING
License-File: COPYING.LESSER
License-File: AUTHORS
Requires-Dist: cycler (==0.11.0)
Requires-Dist: dill (==0.3.4)
Requires-Dist: fonttools (==4.28.5)
Requires-Dist: grpcio (==1.43.0)
Requires-Dist: grpcio-tools (==1.43.0)
Requires-Dist: h5py (==3.6.0)
Requires-Dist: kiwisolver (==1.3.2)
Requires-Dist: matplotlib (==3.5.1)
Requires-Dist: multiprocess (==0.70.12.2)
Requires-Dist: numpy (==1.21.5)
Requires-Dist: packaging (==21.3)
Requires-Dist: pathos (==0.2.8)
Requires-Dist: Pillow (==9.0.1)
Requires-Dist: pox (==0.3.0)
Requires-Dist: ppft (==1.6.6.4)
Requires-Dist: protobuf (==3.19.1)
Requires-Dist: psutil (==5.8.0)
Requires-Dist: PyOpenGL (==3.1.5)
Requires-Dist: pyparsing (==3.0.6)
Requires-Dist: PyQt5 (==5.15.6)
Requires-Dist: PyQt5-Qt5 (==5.15.2)
Requires-Dist: PyQt5-sip (==12.9.0)
Requires-Dist: pyqtgraph (==0.12.3)
Requires-Dist: python-dateutil (==2.8.2)
Requires-Dist: qimage2ndarray (==1.8.3)
Requires-Dist: QtPy (==2.0.0)
Requires-Dist: scipy (==1.7.3)
Requires-Dist: six (==1.16.0)
Requires-Dist: gpi-core
